{
  "hadithId": 1003,
  "hadithNo": 11,
  "hadithReferences": {
    "sunnah.com": [""],
    "kitabId": 9,
    "inKitabBab": 1,
    "arabicBook": "",
    "babId": 79
  },
  "name": {
    "arabic": " وَعَنْ أَنَسٍ ‏- رضى الله عنه ‏- { أَنَّ اَلرُّبَيِّعَ بِنْتَ اَلنَّضْرِ ‏-عَمَّتَهُ‏- كَسَرَتْ ثَنِيَّةَ جَارِيَةٍ, فَطَلَبُوا إِلَيْهَا اَلْعَفْوَ, فَأَبَوْا, فَعَرَضُوا اَلْأَرْشَ, فَأَبَوْا, فَأَتَوْا رَسُولَ اَللَّهِ ‏- صلى الله عليه وسلم ‏-وَأَبَوْا إِلَّا اَلْقِصَاصَ, فَأَمَرَ رَسُولُ اَللَّهِ ‏- صلى الله عليه وسلم ‏-بِالْقِصَاصِ, فَقَالَ أَنَسُ بْنُ اَلنَّضْرِ: يَا رَسُولَ اَللَّهِ! أَتُكْسَرُ ثَنِيَّةُ اَلرُّبَيِّعِ? لَا, وَاَلَّذِي بَعَثَكَ بِالْحَقِّ, لَا تُكْسَرُ ثَنِيَّتُهَا, فَقَالَ رَسُولُ اَللَّهِ ‏- صلى الله عليه وسلم ‏-"يَا أَنَسُ! كِتَابُ اَللَّهِ: اَلْقِصَاصُ".‏ فَرَضِيَ اَلْقَوْمُ, فَعَفَوْا, فَقَالَ رَسُولُ اَللَّهِ ‏- صلى الله عليه وسلم ‏-: "إِنَّ مِنْ عِبَادِ اَللَّهِ مَنْ لَوْ أَقْسَمَ عَلَى اَللَّهِ لَأَبَرَّهُ".‏ } مُتَّفَقٌ عَلَيْهِ, وَاللَّفْظُ لِلْبُخَارِيِّ ",
    "urdu": " سیدنا انس رضی اللہ عنہ سے روایت ہے کہ ان کی پھوپھی ربیع بنت نضر نے ایک انصاری لڑکی کے دانت توڑ دئیے۔ ربیع کے رشتہ داروں نے اس سے معافی طلب کی تو انہوں نے انکار کر دیا۔ پھر انہوں نے دیت دینے کی پیش کش کی۔ اسے بھی انہوں نے رد کر دیا اور رسول اللہ صلی اللہ علیہ وسلم کی عدالت میں آئے اور قصاص کا مطالبہ کیا اور قصاص کے سوا کسی بھی چیز کو لینے سے انکار کر دیا تو رسول اللہ صلی اللہ علیہ وسلم نے قصاص کا فیصلہ فرما دیا۔ یہ سن کر سیدنا انس بن نضر نے عرض کیا اے اللہ کے رسول! کیا ربیع کا دانت توڑا جائے گا؟ نہیں، اس ذات اقدس کی قسم جس نے آپ صلی اللہ علیہ وسلم کو حق دے کر مبعوث فرمایا ہے اس کا دانت نہیں توڑا جائے گا۔ یہ سن کر رسول اللہ صلی اللہ علیہ وسلم نے فرمایا ” اے انس! اللہ کا نوشتہ تو قصاص ہی ہے۔ اتنے میں وہ لوگ اس پر رضامند ہو گئے اور پھر معافی دے دی۔“ پس رسول اللہ صلی اللہ علیہ وسلم نے فرمایا ” اللہ کے بندے ایسے بھی ہیں کہ اگر وہ اللہ کی قسم کھا لیتے ہیں تو اللہ تعالیٰ ان کی قسم کو پورا فرما دیتا ہے۔“ (بخاری و مسلم) اور یہ الفاظ بخاری کے ہیں۔ ",
    "english": " "
  },
  "takhreej": {
    "arabic": "صحيح.‏ رواه البخاري (2703)‏، ومسلم (1675)‏.‏ ",
    "urdu": " ",
    "english": " "
  },
  "importantWords": [
    {
      "arabic": " ",
      "english": " ",
      "urdu": " "
    }
  ],
  "summary": {
    "urdu": " ",
    "english": " "
  },
  "references": [
    {
      "arabic": " ",
      "english": " "
    }
  ],
  "narrators": [
    {
      "id": 1,
      "name": {
        "arabic": " ",
        "english": " "
      },
      "slug": " "
    }
  ],
  "ytLink": " ",
  "grade": {
    "arabic": " ",
    "english": " "
  },

  "explanation": [
    {
      "sectionTitle": {
        "urdu": "",
        "english": ""
      },
      "sectionData": {
        "points": [
          {
            "title": {
              "urdu": "",
              "english": ""
            },
            "content": {
              "urdu": ["", "", ""],
              "english": ["", "", ""]
            }
          },
          {
            "title": {
              "urdu": " ",
              "english": ""
            },
            "content": {
              "urdu": ["", "", ""],
              "english": ["", "", ""]
            }
          }
        ]
      }
    },
    {
      "sectionTitle": {
        "urdu": "",
        "english": ""
      },
      "sectionData": {
        "points": [
          {
            "title": {
              "urdu": "",
              "english": ""
            },
            "content": {
              "urdu": ["", "", ""],
              "english": ["", "", ""]
            }
          },
          {
            "title": {
              "urdu": " ",
              "english": ""
            },
            "content": {
              "urdu": ["", "", ""],
              "english": ["", "", ""]
            }
          }
        ]
      }
    },
    {
      "sectionTitle": {
        "urdu": "",
        "english": ""
      },
      "sectionData": {
        "points": [
          {
            "title": {
              "urdu": "",
              "english": ""
            },
            "content": {
              "urdu": ["", "", ""],
              "english": ["", "", ""]
            }
          },
          {
            "title": {
              "urdu": " ",
              "english": ""
            },
            "content": {
              "urdu": ["", "", ""],
              "english": ["", "", ""]
            }
          }
        ]
      }
    },
    {
      "sectionTitle": {
        "urdu": "",
        "english": ""
      },
      "sectionData": {
        "points": [
          {
            "title": {
              "urdu": "",
              "english": ""
            },
            "content": {
              "urdu": ["", "", ""],
              "english": ["", "", ""]
            }
          },
          {
            "title": {
              "urdu": " ",
              "english": ""
            },
            "content": {
              "urdu": ["", "", ""],
              "english": ["", "", ""]
            }
          }
        ]
      }
    }
  ]
}
