{
  "hadithId": 451,
  "hadithNo": 27,
  "hadithReferences": {
    "sunnah.com": [""],
    "kitabId": 3,
    "inKitabBab": 1,
    "arabicBook": "",
    "babId": 28
  },
  "name": {
    "arabic": " وَعَنْ سَمُرَةَ بْنِ جُنْدُبٍ  - رضى الله عنه  - قَالَ: { صَلَّيْتُ وَرَاءَ اَلنَّبِيِّ  - صلى الله عليه وسلم  -عَلَى امْرَأَةٍ مَاتَتْ فِي نِفَاسِهَا, فَقَامَ وَسْطَهَا } مُتَّفَقٌ عَلَيْهِ ",
    "urdu": "سیدنا سمرہ بن جندب رضی اللہ عنہ سے مروی ہے کہ میں نے نبی کریم صلی اللہ علیہ وسلم کے پیچھے ایک ایسی عورت کی نماز جنازہ پڑھی جو حالت نفاس میں فوت ہوئی تھی۔ آپ صلی اللہ علیہ وسلم اس کے درمیان میں کھڑے ہوئے تھے۔ (بخاری و مسلم) ",
    "english": " "
  },
  "takhreej": {
    "arabic": " صحيح.  رواه البخاري (3/201/فتح) ، ومسلم (964) . ",
    "urdu": " ",
    "english": " "
  },
  "importantWords": [
    {
      "arabic": " ",
      "english": " ",
      "urdu": " "
    }
  ],
  "summary": {
    "urdu": " ",
    "english": " "
  },
  "references": [
    {
      "arabic": " ",
      "english": " "
    }
  ],
  "narrators": [
    {
      "id": 1,
      "name": {
        "arabic": " ",
        "english": " "
      },
      "slug": " "
    }
  ],
  "ytLink": " ",
  "grade": {
    "arabic": " ",
    "english": " "
  },

  "explanation": [
    {
      "sectionTitle": {
        "urdu": "",
        "english": ""
      },
      "sectionData": {
        "points": [
          {
            "title": {
              "urdu": "",
              "english": ""
            },
            "content": {
              "urdu": ["", "", ""],
              "english": ["", "", ""]
            }
          },
          {
            "title": {
              "urdu": " ",
              "english": ""
            },
            "content": {
              "urdu": ["", "", ""],
              "english": ["", "", ""]
            }
          }
        ]
      }
    },
    {
      "sectionTitle": {
        "urdu": "",
        "english": ""
      },
      "sectionData": {
        "points": [
          {
            "title": {
              "urdu": "",
              "english": ""
            },
            "content": {
              "urdu": ["", "", ""],
              "english": ["", "", ""]
            }
          },
          {
            "title": {
              "urdu": " ",
              "english": ""
            },
            "content": {
              "urdu": ["", "", ""],
              "english": ["", "", ""]
            }
          }
        ]
      }
    },
    {
      "sectionTitle": {
        "urdu": "",
        "english": ""
      },
      "sectionData": {
        "points": [
          {
            "title": {
              "urdu": "",
              "english": ""
            },
            "content": {
              "urdu": ["", "", ""],
              "english": ["", "", ""]
            }
          },
          {
            "title": {
              "urdu": " ",
              "english": ""
            },
            "content": {
              "urdu": ["", "", ""],
              "english": ["", "", ""]
            }
          }
        ]
      }
    },
    {
      "sectionTitle": {
        "urdu": "",
        "english": ""
      },
      "sectionData": {
        "points": [
          {
            "title": {
              "urdu": "",
              "english": ""
            },
            "content": {
              "urdu": ["", "", ""],
              "english": ["", "", ""]
            }
          },
          {
            "title": {
              "urdu": " ",
              "english": ""
            },
            "content": {
              "urdu": ["", "", ""],
              "english": ["", "", ""]
            }
          }
        ]
      }
    }
  ]
}
