{
  "hadithId": 1210,
  "hadithNo": 1,
  "hadithReferences": {
    "sunnah.com": [""],
    "kitabId": 14,
    "inKitabBab": 3,
    "arabicBook": "",
    "babId": 99
  },
  "name": {
    "arabic": " عَنِ ابْنِ عَبَّاسٍ رَضِيَ اَللَّهُ عَنْهُمَا; أَنَّ اَلنَّبِيَّ ‏- صلى الله عليه وسلم ‏-قَالَ: { "لَوْ يُعْطَى اَلنَّاسُ بِدَعْوَاهُمْ, لَادَّعَى نَاسٌ دِمَاءَ رِجَالٍ, وَأَمْوَالَهُمْ, وَلَكِنِ اَلْيَمِينُ عَلَى اَلْمُدَّعَى عَلَيْهِ" } مُتَّفَقٌ عَلَيْه ِ 1‏ وَلِلْبَيْهَقِيِّ بِإِسْنَادٍ صَحِيحٍ: { "اَلْبَيِّنَةُ عَلَى اَلْمُدَّعِي, وَالْيَمِينُ عَلَى مَنْ أَنْكَرَ }",
    "urdu": " سیدنا ابن عباس رضی اللہ عنہما سے مروی ہے کہ نبی کریم صلی اللہ علیہ وسلم نے فرمایا ” اگر لوگوں کو محض ان کے دعوے کرنے سے حق دے دیا جائے تو لوگ دوسرے لوگوں کے خون اور ان کے اموال کا دعویٰ کریں گے لیکن مدعا علیہ کے ذمہ قسم لازم ہے۔“ (بخاری و مسلم) اور بیہقی نے صحیح سند سے روایت کیا ہے کہ گواہی (یا دلیل) مدعی کے ذمہ اور قسم اس کے ذمہ جو اس کا انکار کرے۔",
    "english": " "
  },
  "takhreej": {
    "arabic": " صحيح.‏ رواه البخاري ( 4552 )‏، ومسلم ( 1711 )‏ والسياق لمسلم، وفيه عند البخاري قصة.‏
‏2 ‏- صحيح.‏ رواه البيهقي ( 10 / 252 )‏ وهو قطعة من الحديث السابق، وله شواهد عن غير ابن عباس.‏",
    "urdu": " ",
    "english": " "
  },
  "importantWords": [
    {
      "arabic": " ",
      "english": " ",
      "urdu": " "
    }
  ],
  "summary": {
    "urdu": " ",
    "english": " "
  },
  "references": [
    {
      "arabic": " ",
      "english": " "
    }
  ],
  "narrators": [
    {
      "id": 1,
      "name": {
        "arabic": " ",
        "english": " "
      },
      "slug": " "
    }
  ],
  "ytLink": " ",
  "grade": {
    "arabic": " ",
    "english": " "
  },

  "explanation": [
    {
      "sectionTitle": {
        "urdu": "",
        "english": ""
      },
      "sectionData": {
        "points": [
          {
            "title": {
              "urdu": "",
              "english": ""
            },
            "content": {
              "urdu": ["", "", ""],
              "english": ["", "", ""]
            }
          },
          {
            "title": {
              "urdu": " ",
              "english": ""
            },
            "content": {
              "urdu": ["", "", ""],
              "english": ["", "", ""]
            }
          }
        ]
      }
    },
    {
      "sectionTitle": {
        "urdu": "",
        "english": ""
      },
      "sectionData": {
        "points": [
          {
            "title": {
              "urdu": "",
              "english": ""
            },
            "content": {
              "urdu": ["", "", ""],
              "english": ["", "", ""]
            }
          },
          {
            "title": {
              "urdu": " ",
              "english": ""
            },
            "content": {
              "urdu": ["", "", ""],
              "english": ["", "", ""]
            }
          }
        ]
      }
    },
    {
      "sectionTitle": {
        "urdu": "",
        "english": ""
      },
      "sectionData": {
        "points": [
          {
            "title": {
              "urdu": "",
              "english": ""
            },
            "content": {
              "urdu": ["", "", ""],
              "english": ["", "", ""]
            }
          },
          {
            "title": {
              "urdu": " ",
              "english": ""
            },
            "content": {
              "urdu": ["", "", ""],
              "english": ["", "", ""]
            }
          }
        ]
      }
    },
    {
      "sectionTitle": {
        "urdu": "",
        "english": ""
      },
      "sectionData": {
        "points": [
          {
            "title": {
              "urdu": "",
              "english": ""
            },
            "content": {
              "urdu": ["", "", ""],
              "english": ["", "", ""]
            }
          },
          {
            "title": {
              "urdu": " ",
              "english": ""
            },
            "content": {
              "urdu": ["", "", ""],
              "english": ["", "", ""]
            }
          }
        ]
      }
    }
  ]
}
